dkbotzdb/__init__.py
dkbotzdb-1.0.3.dist-info/licenses/LICENSE
dkbotzdb-1.0.3.dist-info/METADATA
dkbotzdb-1.0.3.dist-info/WHEEL
dkbotzdb-1.0.3.dist-info/top_level.txt
dkbotzdb-1.0.3.dist-info/RECORD
