Metadata-Version: 2.4
Name: dkbotzdb
Version: 1.0.3
Summary: DkBotzDB Is The Most Powerful And Developer-Friendly Database Solution Powered By DKBotz And DkBotzPro, Offering Fast, Reliable, Scalable, And Secure Data Management. Designed For Effortless Integration And Built With Modern API Standards, DkBotzDB Ensures Smooth Performance Across Applications, Backed By The Trust And Excellence of dkbotzpro.in.
Home-page: https://github.com/DKBOTZPROJECT/DKBOTZDB
Author: DKBOTZ
License: GNU AFFERO GENERAL PUBLIC LICENSE (v3)
Classifier: Programming Language :: Python :: 3
Classifier: Programming Language :: Python :: 3.6
Classifier: Programming Language :: Python :: 3.7
Classifier: Programming Language :: Python :: 3.8
Classifier: Programming Language :: Python :: 3.9
Classifier: License :: OSI Approved :: GNU General Public License v3 (GPLv3)
Classifier: Operating System :: OS Independent
Requires-Python: >=3.6
License-File: LICENSE
Requires-Dist: requests
Requires-Dist: colorlog
Dynamic: author
Dynamic: classifier
Dynamic: description
Dynamic: description-content-type
Dynamic: home-page
Dynamic: license
Dynamic: license-file
Dynamic: requires-dist
Dynamic: requires-python
Dynamic: summary
